Metadata-Version: 1.2
Name: django-feature-toggle
Version: 0.2.0
Summary: A simple Django app based on Feature Toggle described by Martin Fowler.
Home-page: https://github.com/thulasi-ram/django-feature-toggle
Author: Damodharan Thulasiram
Author-email: thulasi503@gmail.com
License: GNU GPLv3
Project-URL: Documentation, https://thulasi-ram.github.io/django-feature-toggle
Project-URL: Source, https://github.com/thulasi-ram/django-feature-toggle
Project-URL: Tracker, https://github.com/thulasi-ram/django-feature-toggle/issues
Keywords: django feature toggle switch
Platform: UNKNOWN
Classifier: Environment :: Web Environment
Classifier: Framework :: Django
Classifier: Framework :: Django :: 1.11
Classifier: Intended Audience :: Developers
Classifier: License :: OSI Approved :: GNU General Public License v3 (GPLv3)
Classifier: Operating System :: OS Independent
Classifier: Programming Language :: Python
Classifier: Programming Language :: Python :: 2.7
Classifier: Programming Language :: Python :: 3
Classifier: Topic :: Internet :: WWW/HTTP
Classifier: Topic :: Internet :: WWW/HTTP :: Dynamic Content
Requires-Python: >=2.7, !=3.0.*, !=3.1.*, !=3.2.*, <4
